pydagogy/__init__.py
pydagogy/asserts.py
pydagogy/tests.py
pydagogy/utils.py
pydagogy-0.1.dist-info/METADATA
pydagogy-0.1.dist-info/WHEEL
pydagogy-0.1.dist-info/top_level.txt
pydagogy-0.1.dist-info/RECORD
