Metadata-Version: 2.1
Name: pydagogy
Version: 0.1
Summary: A package for automated feedback in coding exercises.
Home-page: https://github.com/mcleonard/pydagogy
Author: Mat Leonard
Author-email: leonard.mat@gmail.com.com
License: UNKNOWN
Platform: UNKNOWN
Classifier: Programming Language :: Python :: 3
Classifier: License :: OSI Approved :: MIT License
Classifier: Operating System :: OS Independent
Requires-Python: >=3.6
